.gitignore
.installed.cfg
MANIFEST.in
README.txt
bootstrap.py
buildout.cfg
setup.py
docs/HISTORY.txt
docs/INSTALL.txt
docs/LICENSE.GPL
docs/LICENSE.txt
src/qi/__init__.py
src/qi.portlet.TagClouds.egg-info/PKG-INFO
src/qi.portlet.TagClouds.egg-info/SOURCES.txt
src/qi.portlet.TagClouds.egg-info/dependency_links.txt
src/qi.portlet.TagClouds.egg-info/entry_points.txt
src/qi.portlet.TagClouds.egg-info/namespace_packages.txt
src/qi.portlet.TagClouds.egg-info/not-zip-safe
src/qi.portlet.TagClouds.egg-info/requires.txt
src/qi.portlet.TagClouds.egg-info/top_level.txt
src/qi/portlet/__init__.py
src/qi/portlet/TagClouds/__init__.py
src/qi/portlet/TagClouds/configure.zcml
src/qi/portlet/TagClouds/tagcloudportlet.pt
src/qi/portlet/TagClouds/tagcloudportlet.py
src/qi/portlet/TagClouds/testing.py
src/qi/portlet/TagClouds/update_i18n.sh
src/qi/portlet/TagClouds/vocabularies.py
src/qi/portlet/TagClouds/browser/__init__.py
src/qi/portlet/TagClouds/browser/configure.zcml
src/qi/portlet/TagClouds/browser/stylesheets/tagclouds.css
src/qi/portlet/TagClouds/locales/qi.portlet.TagClouds.pot
src/qi/portlet/TagClouds/locales/cs/LC_MESSAGES/qi.portlet.TagClouds.mo
src/qi/portlet/TagClouds/locales/cs/LC_MESSAGES/qi.portlet.TagClouds.po
src/qi/portlet/TagClouds/locales/de/LC_MESSAGES/qi.portlet.TagClouds.mo
src/qi/portlet/TagClouds/locales/de/LC_MESSAGES/qi.portlet.TagClouds.po
src/qi/portlet/TagClouds/locales/en/LC_MESSAGES/qi.portlet.TagClouds.mo
src/qi/portlet/TagClouds/locales/en/LC_MESSAGES/qi.portlet.TagClouds.po
src/qi/portlet/TagClouds/locales/es/LC_MESSAGES/qi.portlet.TagClouds.mo
src/qi/portlet/TagClouds/locales/es/LC_MESSAGES/qi.portlet.TagClouds.po
src/qi/portlet/TagClouds/locales/eu/LC_MESSAGES/qi.portlet.TagClouds.mo
src/qi/portlet/TagClouds/locales/eu/LC_MESSAGES/qi.portlet.TagClouds.po
src/qi/portlet/TagClouds/locales/fr/LC_MESSAGES/qi.portlet.TagClouds.mo
src/qi/portlet/TagClouds/locales/fr/LC_MESSAGES/qi.portlet.TagClouds.po
src/qi/portlet/TagClouds/locales/pt_BR/LC_MESSAGES/qi.portlet.TagClouds.mo
src/qi/portlet/TagClouds/locales/pt_BR/LC_MESSAGES/qi.portlet.TagClouds.po
src/qi/portlet/TagClouds/locales/zh_TW/LC_MESSAGES/qi.portlet.TagClouds.mo
src/qi/portlet/TagClouds/locales/zh_TW/LC_MESSAGES/qi.portlet.TagClouds.po
src/qi/portlet/TagClouds/profiles/default/cssregistry.xml
src/qi/portlet/TagClouds/profiles/default/metadata.xml
