Metadata-Version: 1.1
Name: qi.portlet.TagClouds
Version: 1.35
Summary: A configurable plone portlet that displays tag clouds
Home-page: http://svn.plone.org/svn/collective/qi.portlet.TagClouds
Author: Yiorgis Gozadinos
Author-email: ggozad@jarn.com
License: GPL
Keywords: plone,tag,cloud,portlet
Platform: Any
Classifier: Environment :: Web Environment
Classifier: Framework :: Plone
Classifier: Intended Audience :: Developers
Classifier: License :: OSI Approved :: GNU General Public License (GPL)
Classifier: Operating System :: OS Independent
Classifier: Programming Language :: Python
Classifier: Topic :: Software Development :: Libraries :: Python Modules
